standard_packages_c/__init__.py
standard_packages_c/core.py
standard_packages_c/log.py
standard_packages_c/server.py
standard_packages_c-0.1.0.dist-info/METADATA
standard_packages_c-0.1.0.dist-info/WHEEL
standard_packages_c-0.1.0.dist-info/top_level.txt
standard_packages_c-0.1.0.dist-info/RECORD
